{
    "positions": {
        "Government and Ministers": {
            "Q1723031": "Primeiro-Ministro de Portugal",
            "Q4294919": "Ministro dos Negócios Estrangeiros",
            "Q43186728": "Ministro da Administração Interna",
            "Q25906445": "Ministro da Defesa Nacional",
            "Q30121475": "Ministro da Educação",
            "Q25917010": "Ministro do Ambiente",
            "Q23196603": "Ministro da Saúde",
            "Q43186489": "Ministro da Justiça",
            "Q25917009": "Ministro do Equipamento Social",
            "Q56872893": "Ministro dos Assuntos Parlamentares",
            "Q61607793": "Ministro para a Igualdade",
            "Q61927426": "Ministro para a Qualificação e o Emprego",
            "Q99281259": "Ministro das Finanças",
            "Q7614320": "Ministro de Economia",
            "Q10353662": "Presidente do Conselho de Ministros de Portugal",
            "Q25909451": "Vice-Primeiro-Ministro de Portugal"
        },
        "Parliament and Republic": {
            "Q25448371": "Presidente da Assembleia da República Portuguesa",
            "Q19953703": "Deputado da Assembleia da República",
            "Q322459": "Presidente da República Portuguesa",
            "Q60999452": "Procurador-geral da República"
        },
        "Regional Governments": {
            "Q98960414": "Presidente do Governo Regional da Madeira",
            "Q99228777": "Presidente do Governo Regional dos Açores",
            "Q62083474": "Deputado da Assembleia Regional dos Açores"
        },
        "Municipalities": {"Q43185970": "Mayor of Lisbon"},
        "Portuguese Parties": {
            "Q82560916": "Presidente do Partido Social Democrata",
            "Q25431489": "Presidente do CDS – Partido Popular",
            "Q27134289": "Secretário-Geral do Partido Socialista",
            "Q82971002": "Presidente do Partido Renovador Democrático",
            "Q81733774": "Secretário-Geral do Partido Comunista Português",
            "Q82563249": "Coordenador Nacional do Bloco de Esquerda"
        },
        "Europa-related positions": {
            "Q8882": "Presidente da Comissão Europeia",
            "Q735587": "Presidência do Conselho Europeu",
            "Q7925068": "Vice-presidente do Parlamento Europeu"
        },
        "Embaixadores": {"Q30061057": "Embaixador de Portugal"},
        "Misc. Public Positions": {
            "Q50362555": "Governador do Banco de Portugal",
            "Q89840006": "Secretário de Estado do Turismo"
        },
        "PALOPS": {
            "Q846091": "Presidente de Angola",
            "Q18565665": "Presidente de Moçambique",
            "Q19058289": "Presidente de São Tomé e Príncipe"
        }
    },
    "persons": {
        "remove": [
            "https://www.wikidata.org/wiki/Q10261673",
            "https://www.wikidata.org/wiki/Q10311834",
            "https://www.wikidata.org/wiki/Q10334555",
            "https://www.wikidata.org/wiki/Q10365336",
            "https://www.wikidata.org/wiki/Q10365348",
            "https://www.wikidata.org/wiki/Q13471235",
            "https://www.wikidata.org/wiki/Q151394",
            "https://www.wikidata.org/wiki/Q20716651",
            "https://www.wikidata.org/wiki/Q241131",
            "https://www.wikidata.org/wiki/Q28226050",
            "https://www.wikidata.org/wiki/Q314022",
            "https://www.wikidata.org/wiki/Q3476927",
            "https://www.wikidata.org/wiki/Q4237195",
            "https://www.wikidata.org/wiki/Q470926",
            "https://www.wikidata.org/wiki/Q5154284",
            "https://www.wikidata.org/wiki/Q7010657",
            "https://www.wikidata.org/wiki/Q7404412",
            "https://www.wikidata.org/wiki/Q741496",
            "https://www.wikidata.org/wiki/Q934065",
            "https://www.wikidata.org/wiki/Q9619550",
            "https://www.wikidata.org/wiki/Q9620029",
            "https://www.wikidata.org/wiki/Q9697198"
        ],
        "add": [
            "https://www.wikidata.org/wiki/Q312556",
            "https://www.wikidata.org/wiki/Q6279",
            "https://www.wikidata.org/wiki/Q5284",
            "https://www.wikidata.org/wiki/Q180589",
            "https://www.wikidata.org/wiki/Q10325927",
            "https://www.wikidata.org/wiki/Q39259",
            "https://www.wikidata.org/wiki/Q6294",
            "https://www.wikidata.org/wiki/Q43723",
            "https://www.wikidata.org/wiki/Q61053",
            "https://www.wikidata.org/wiki/Q359442",
            "https://www.wikidata.org/wiki/Q13424289",
            "https://www.wikidata.org/wiki/Q19837",
            "https://www.wikidata.org/wiki/Q57641",
            "https://www.wikidata.org/wiki/Q3874799",
            "https://www.wikidata.org/wiki/Q36215",
            "https://www.wikidata.org/wiki/Q3099714",
            "https://www.wikidata.org/wiki/Q155979",
            "https://www.wikidata.org/wiki/Q123738046",
            "https://www.wikidata.org/wiki/Q10325927",
            "https://www.wikidata.org/wiki/Q40688",
            "https://www.wikidata.org/wiki/Q9619875",
            "https://www.wikidata.org/wiki/Q10272593",
            "https://www.wikidata.org/wiki/Q10304982",
            "https://www.wikidata.org/wiki/Q10325927",
            "https://www.wikidata.org/wiki/Q10819",
            "https://www.wikidata.org/wiki/Q11665",
            "https://www.wikidata.org/wiki/Q1253",
            "https://www.wikidata.org/wiki/Q13581707",
            "https://www.wikidata.org/wiki/Q1567582",
            "https://www.wikidata.org/wiki/Q157",
            "https://www.wikidata.org/wiki/Q16019",
            "https://www.wikidata.org/wiki/Q2254113",
            "https://www.wikidata.org/wiki/Q22686",
            "https://www.wikidata.org/wiki/Q23778050",
            "https://www.wikidata.org/wiki/Q264766",
            "https://www.wikidata.org/wiki/Q294460",
            "https://www.wikidata.org/wiki/Q3052772",
            "https://www.wikidata.org/wiki/Q312015",
            "https://www.wikidata.org/wiki/Q312831",
            "https://www.wikidata.org/wiki/Q3186200",
            "https://www.wikidata.org/wiki/Q329",
            "https://www.wikidata.org/wiki/Q37181",
            "https://www.wikidata.org/wiki/Q40722",
            "https://www.wikidata.org/wiki/Q456034",
            "https://www.wikidata.org/wiki/Q463533",
            "https://www.wikidata.org/wiki/Q5041962",
            "https://www.wikidata.org/wiki/Q567",
            "https://www.wikidata.org/wiki/Q60780752",
            "https://www.wikidata.org/wiki/Q76",
            "https://www.wikidata.org/wiki/Q7747",
            "https://www.wikidata.org/wiki/Q91901804",
            "http://www.wikidata.org/entity/Q10332811",
            "http://www.wikidata.org/entity/Q10345627",
            "http://www.wikidata.org/entity/Q10284314",
            "http://www.wikidata.org/entity/Q1054298",
            "http://www.wikidata.org/entity/Q1134161",
            "http://www.wikidata.org/entity/Q1259087",
            "http://www.wikidata.org/entity/Q1276673",
            "http://www.wikidata.org/entity/Q1332539",
            "http://www.wikidata.org/entity/Q1344670",
            "http://www.wikidata.org/entity/Q138198",
            "http://www.wikidata.org/entity/Q14924303",
            "http://www.wikidata.org/entity/Q1546030",
            "http://www.wikidata.org/entity/Q156868",
            "http://www.wikidata.org/entity/Q16947563",
            "http://www.wikidata.org/entity/Q1851550",
            "http://www.wikidata.org/entity/Q19694667",
            "http://www.wikidata.org/entity/Q2031598",
            "http://www.wikidata.org/entity/Q2054628",
            "http://www.wikidata.org/entity/Q2054681",
            "http://www.wikidata.org/entity/Q2054807",
            "http://www.wikidata.org/entity/Q206682",
            "http://www.wikidata.org/entity/Q208242",
            "http://www.wikidata.org/entity/Q2119074",
            "http://www.wikidata.org/entity/Q222897",
            "http://www.wikidata.org/entity/Q2366265",
            "http://www.wikidata.org/entity/Q28551",
            "http://www.wikidata.org/entity/Q3112915",
            "http://www.wikidata.org/entity/Q327591",
            "http://www.wikidata.org/entity/Q377349",
            "http://www.wikidata.org/entity/Q46122950",
            "http://www.wikidata.org/entity/Q47729",
            "http://www.wikidata.org/entity/Q49762",
            "http://www.wikidata.org/entity/Q504564",
            "http://www.wikidata.org/entity/Q572998",
            "http://www.wikidata.org/entity/Q595575",
            "http://www.wikidata.org/entity/Q61046702",
            "http://www.wikidata.org/entity/Q63645885",
            "http://www.wikidata.org/entity/Q65164025",
            "http://www.wikidata.org/entity/Q657089",
            "http://www.wikidata.org/entity/Q7232654",
            "http://www.wikidata.org/entity/Q750673",
            "http://www.wikidata.org/entity/Q769829",
            "http://www.wikidata.org/entity/Q815348",
            "http://www.wikidata.org/entity/Q847263",
            "http://www.wikidata.org/entity/Q884840",
            "http://www.wikidata.org/entity/Q978086",
            "http://www.wikidata.org/entity/Q980864",
            "http://www.wikidata.org/entity/Q2054840",
            "https://www.wikidata.org/wiki/Q58132",
            "https://www.wikidata.org/wiki/Q2643773",
            "https://www.wikidata.org/wiki/Q72310730",
            "https://www.wikidata.org/wiki/Q97736572",
            "https://www.wikidata.org/wiki/Q10308719",
            "https://www.wikidata.org/wiki/Q15267277",
            "https://www.wikidata.org/wiki/Q207",
            "https://www.wikidata.org/wiki/Q8440",
            "https://www.wikidata.org/wiki/Q192",
            "https://www.wikidata.org/wiki/Q12927",
            "https://www.wikidata.org/wiki/Q34211",
            "https://www.wikidata.org/wiki/Q9545",
            "https://www.wikidata.org/wiki/Q11256",
            "https://www.wikidata.org/wiki/Q60206",
            "https://www.wikidata.org/wiki/Q37060",
            "https://www.wikidata.org/wiki/Q1124",
            "https://www.wikidata.org/wiki/Q1033303",
            "https://www.wikidata.org/wiki/Q10390",
            "https://www.wikidata.org/wiki/Q1316",
            "https://www.wikidata.org/wiki/Q8023",
            "https://www.wikidata.org/wiki/Q46809",
            "https://www.wikidata.org/wiki/Q1254",
            "https://www.wikidata.org/wiki/Q150851",
            "https://www.wikidata.org/wiki/Q2105",
            "https://www.wikidata.org/wiki/Q19878",
            "https://www.wikidata.org/wiki/Q127998",
            "https://www.wikidata.org/wiki/Q230578",
            "https://www.wikidata.org/wiki/Q79983",
            "https://www.wikidata.org/wiki/Q10309301",
            "https://www.wikidata.org/wiki/Q1317",
            "https://www.wikidata.org/wiki/Q10707",
            "https://www.wikidata.org/wiki/Q151394",
            "https://www.wikidata.org/wiki/Q47904",
            "https://www.wikidata.org/wiki/Q6949714",
            "https://www.wikidata.org/wiki/Q273051",
            "https://www.wikidata.org/wiki/Q9013656",
            "https://www.wikidata.org/wiki/Q34105",
            "https://www.wikidata.org/wiki/Q714173",
            "https://www.wikidata.org/wiki/Q2518",
            "https://www.wikidata.org/wiki/Q3302199",
            "https://www.wikidata.org/wiki/Q10324486",
            "https://www.wikidata.org/wiki/Q184650",
            "https://www.wikidata.org/wiki/Q13989269",
            "https://www.wikidata.org/wiki/Q334835",
            "https://www.wikidata.org/wiki/Q221997",
            "https://www.wikidata.org/wiki/Q6298213",
            "https://www.wikidata.org/wiki/Q107431",
            "https://www.wikidata.org/wiki/Q7195700",
            "https://www.wikidata.org/wiki/Q1392332",
            "https://www.wikidata.org/wiki/Q10270753",
            "https://www.wikidata.org/wiki/Q368",
            "https://www.wikidata.org/wiki/Q44851",
            "https://www.wikidata.org/wiki/Q10308796",
            "https://www.wikidata.org/wiki/Q500378",
            "https://www.wikidata.org/wiki/Q66107",
            "https://www.wikidata.org/wiki/Q712532",
            "https://www.wikidata.org/wiki/Q349583",
            "https://www.wikidata.org/wiki/Q362274",
            "https://www.wikidata.org/wiki/Q45043",
            "https://www.wikidata.org/wiki/Q518861",
            "https://www.wikidata.org/wiki/Q10313446",
            "https://www.wikidata.org/wiki/Q106164",
            "https://www.wikidata.org/wiki/Q82322",
            "https://www.wikidata.org/wiki/Q10316578",
            "https://www.wikidata.org/wiki/Q27134712",
            "https://www.wikidata.org/wiki/Q336238",
            "https://www.wikidata.org/wiki/Q47139",
            "https://www.wikidata.org/wiki/Q485946",
            "https://www.wikidata.org/wiki/Q57517",
            "https://www.wikidata.org/wiki/Q905",
            "https://www.wikidata.org/wiki/Q10343426",
            "https://www.wikidata.org/wiki/Q123923",
            "https://www.wikidata.org/wiki/Q348880",
            "https://www.wikidata.org/wiki/Q356691",
            "https://www.wikidata.org/wiki/Q603534",
            "https://www.wikidata.org/wiki/Q6205665",
            "https://www.wikidata.org/wiki/Q10311869",
            "https://www.wikidata.org/wiki/Q10355764",
            "https://www.wikidata.org/wiki/Q19607921",
            "https://www.wikidata.org/wiki/Q265277",
            "https://www.wikidata.org/wiki/Q9682",
            "https://www.wikidata.org/wiki/Q10324229",
            "https://www.wikidata.org/wiki/Q235866",
            "https://www.wikidata.org/wiki/Q37349",
            "https://www.wikidata.org/wiki/Q777954",
            "https://www.wikidata.org/wiki/Q957483",
            "https://www.wikidata.org/wiki/Q983957"
        ]
    }
}
